graphsense/__init__.py
graphsense/graphsense.py
graphsense-0.0.3.dist-info/LICENSE
graphsense-0.0.3.dist-info/METADATA
graphsense-0.0.3.dist-info/WHEEL
graphsense-0.0.3.dist-info/top_level.txt
graphsense-0.0.3.dist-info/RECORD
