Metadata-Version: 2.2
Name: graphsense
Version: 0.0.3
Summary: GraphSense is a framework that can be used to easily train and use code suggestion models with minimal data preprocessing and resource consumption
Home-page: https://github.com/NavodPeiris/graphsense
Author: Navod Peiris
Author-email: navodpeiris1234@gmail.com
License: MIT
Classifier: License :: OSI Approved :: MIT License
Classifier: Programming Language :: Python :: 3.10
Classifier: Operating System :: OS Independent
Requires-Python: >=3.8
License-File: LICENSE
Requires-Dist: numpy
Requires-Dist: pecanpy
Requires-Dist: gensim
Requires-Dist: onnxruntime
Requires-Dist: onnxruntime-gpu
Requires-Dist: scikit-learn
Requires-Dist: faiss-cpu
Requires-Dist: rocksdb-py
Requires-Dist: light_embed
Dynamic: author
Dynamic: author-email
Dynamic: classifier
Dynamic: description
Dynamic: description-content-type
Dynamic: home-page
Dynamic: license
Dynamic: requires-dist
Dynamic: requires-python
Dynamic: summary
